[
    {
        "data": {
            "id": 0,
            "color": [255, 0, 0, 255],
            "amount": 100,
            "radius": 5000,
            "path": [
                [
                    -101.8139850244877,
                    21.91007385880703
                ],
                [
                    -101.16743250019897,
                    25.689506661422172
                ],
                [
                    -91.59519664340208,
                    31.832465500477092
                ],
                [
                    -99.5460777085208,
                    29.205092989438985
                ],
                [
                    -101.80279469233668,
                    23.33942713350117
                ],
                [
                    -100.96538483635868,
                    26.40012487041532
                ],
                [
                    -101.88734386858978,
                    22.90186104588809
                ],
                [
                    -82.34238896364334,
                    29.326431553715697
                ],
                [
                    -98.73788705315971,
                    29.721096373087626
                ],
                [
                    -101.35331635093203,
                    25.035737909148477
                ],
                [
                    -86.7305533796942,
                    31.00171219493018
                ],
                [
                    -99.94644292548426,
                    28.428231775455753
                ],
                [
                    -97.2850089288683,
                    30.57932569919479
                ],
                [
                    -92.0846421352404,
                    31.916773879798512
                ],
                [
                    -100.06083298747383,
                    28.206271428603404
                ],
                [
                    -89.80056317332821,
                    31.523334776298558
                ],
                [
                    -100.81866714815467,
                    26.735784130706573
                ],
                [
                    -85.1119961710538,
                    30.87041568631178
                ],
                [
                    -82.75674209579581,
                    30.338156546572623
                ],
                [
                    -91.70396230825504,
                    31.851200695881854
                ],
                [
                    -92.19340780009337,
                    31.93550907520327
                ],
                [
                    -95.62386628954151,
                    31.393763231840968
                ],
                [
                    -91.59519664340208,
                    31.832465500477092
                ],
                [
                    -98.48983469047582,
                    29.867623331203482
                ],
                [
                    -101.95759428709418,
                    22.357842458597567
                ],
                [
                    -101.0462039018948,
                    26.11587758681806
                ],
                [
                    -86.65159936951662,
                    30.9953074871927
                ],
                [
                    -101.37756207059287,
                    24.950463724069298
                ],
                [
                    -89.36550051391637,
                    31.44839399467952
                ],
                [
                    -99.66046777051035,
                    28.983132642586632
                ]
            ],
            "timestamps": [
                1674432000,
                1679875200,
                1680393600,
                1680652800,
                1681516800,
                1681689600,
                1681776000,
                1682640000,
                1682640000,
                1683158400,
                1683504000,
                1684972800,
                1685059200,
                1685404800,
                1686441600,
                1687046400,
                1695513600,
                1695686400,
                1695772800,
                1696550400,
                1697587200,
                1698710400,
                1698883200,
                1699401600,
                1699574400,
                1699833600,
                1700092800,
                1700438400,
                1700784000,
                1703116800
            ]
        }
    },
    {
        "data": {
            "id": 1,
            "color": [255, 0, 0, 255],
            "amount": 100,
            "radius": 5000,
            "path": [
                [
                    -101.78123928043567,
                    21.624399707112868
                ],
                [
                    -101.80735005545503,
                    21.709265151308205
                ],
                [
                    -101.72031413872384,
                    21.42638033732375
                ],
                [
                    -100.85337423956925,
                    31.440798047663044
                ],
                [
                    -101.92951118143841,
                    22.90263237533279
                ],
                [
                    -100.97273778251459,
                    27.930060938193538
                ],
                [
                    -101.70383948305674,
                    23.761788827865885
                ],
                [
                    -101.70383948305674,
                    23.761788827865885
                ],
                [
                    -101.98142188891742,
                    22.27503477927712
                ],
                [
                    -104.04856664716692,
                    39.82458934585652
                ],
                [
                    -109.13127397593391,
                    46.57176546048728
                ],
                [
                    -102.75535788481285,
                    37.06197192007605
                ],
                [
                    -102.92734472788807,
                    37.434797741579175
                ],
                [
                    -107.30308690843697,
                    44.92379482925086
                ],
                [
                    -103.07783321557889,
                    37.761020335394406
                ],
                [
                    -107.56850891145213,
                    45.182699153997646
                ],
                [
                    -104.04856664716692,
                    39.82458934585652
                ],
                [
                    -104.15027040533161,
                    39.9839395172126
                ],
                [
                    -103.24982005865411,
                    38.13384615689753
                ],
                [
                    -105.57412301963726,
                    42.21484191619762
                ],
                [
                    -101.95991873558997,
                    35.3376524956241
                ],
                [
                    -105.74362928324507,
                    42.480425535124404
                ],
                [
                    -106.86237062305665,
                    44.23327742004121
                ],
                [
                    -105.23511049242163,
                    41.68367467834404
                ],
                [
                    -103.80877729864858,
                    39.34553007678268
                ],
                [
                    -100.96714261643903,
                    28.09462674019992
                ],
                [
                    -100.99511844681685,
                    27.271797730168007
                ],
                [
                    -101.95966290973462,
                    22.204313575781008
                ],
                [
                    -101.90899557249463,
                    22.980737507381253
                ],
                [
                    -101.75512850541621,
                    23.566525997744726
                ]
            ],
            "timestamps": [
                1676246400,
                1677456000,
                1679356800,
                1680480000,
                1682640000,
                1683849600,
                1684886400,
                1686528000,
                1687046400,
                1687651200,
                1687996800,
                1688688000,
                1689206400,
                1689379200,
                1689984000,
                1690416000,
                1690934400,
                1691107200,
                1691712000,
                1692057600,
                1693699200,
                1693785600,
                1694304000,
                1694390400,
                1694649600,
                1696982400,
                1697068800,
                1698451200,
                1699488000,
                1700352000
            ]
        }
    },
    {
        "data": {
            "id": 2,
            "color": [255, 0, 0, 255],
            "amount": 100,
            "radius": 5000,
            "path": [
                [
                    -101.83981658294931,
                    21.245769743075208
                ],
                [
                    -101.8524183074466,
                    21.30694877544511
                ],
                [
                    -101.98788684579249,
                    21.964623373421553
                ],
                [
                    -101.88707304981415,
                    21.47519111446234
                ],
                [
                    -101.89022348093847,
                    21.490485872554814
                ],
                [
                    -101.95638253454925,
                    21.811675792496796
                ],
                [
                    -102.12020495301404,
                    22.607003213305518
                ],
                [
                    -98.00121696890685,
                    33.44271963672689
                ],
                [
                    -102.08239977952216,
                    22.42346611619581
                ],
                [
                    -100.41432839066927,
                    28.5067249055656
                ],
                [
                    -102.12020495301404,
                    22.607003213305518
                ],
                [
                    -100.8273745054501,
                    27.051195783077016
                ],
                [
                    -99.63780169488132,
                    31.243119655844147
                ],
                [
                    -101.22039335573649,
                    25.688785968268235
                ],
                [
                    -92.10132977476127,
                    38.69156872342966
                ],
                [
                    -91.88340201842219,
                    38.87956087751777
                ],
                [
                    -92.0468478356765,
                    38.73856676195169
                ],
                [
                    -97.25557461654891,
                    34.10813173440167
                ],
                [
                    -91.85616104887981,
                    38.90305989677878
                ],
                [
                    -91.77443814025266,
                    38.97355695456182
                ],
                [
                    -92.50994431789705,
                    38.33908343451446
                ],
                [
                    -91.5020284448288,
                    39.208547147171956
                ],
                [
                    -101.82406442732776,
                    23.621260828862866
                ],
                [
                    -100.13345703261831,
                    29.496484708857842
                ],
                [
                    -100.24910994475694,
                    29.088936554561037
                ],
                [
                    -101.2659534366113,
                    25.532746335105564
                ],
                [
                    -99.65432353947256,
                    31.1848984909446
                ],
                [
                    -101.00398297158112,
                    26.429974225790914
                ],
                [
                    -97.59450295852979,
                    33.80567169000404
                ],
                [
                    -102.00678943253843,
                    22.056391921976402
                ]
            ],
            "timestamps": [
                1672963200,
                1675382400,
                1676246400,
                1677801600,
                1679097600,
                1679270400,
                1680048000,
                1680652800,
                1682121600,
                1684368000,
                1685577600,
                1686009600,
                1686182400,
                1686873600,
                1687564800,
                1689552000,
                1689811200,
                1690588800,
                1691280000,
                1692057600,
                1692316800,
                1695254400,
                1696204800,
                1697673600,
                1698019200,
                1698537600,
                1699488000,
                1700524800,
                1701993600,
                1702944000
            ]
        }
    },
    {
        "data": {
            "id": 3,
            "color": [255, 0, 0, 255],
            "amount": 100,
            "radius": 5000,
            "path": [
                [
                    -101.96446128186469,
                    21.538583937741727
                ],
                [
                    -101.97206341289976,
                    21.55384494065068
                ],
                [
                    -102.16211668877683,
                    21.935370013374545
                ],
                [
                    -106.19314667013049,
                    26.859135531887336
                ],
                [
                    -102.6182445508818,
                    22.851030187911817
                ],
                [
                    -102.22293373705749,
                    22.05745803664618
                ],
                [
                    -102.56502963363621,
                    22.744203167549134
                ],
                [
                    -102.37497635775915,
                    22.362678094825274
                ],
                [
                    -102.24574013016274,
                    22.103241045373046
                ],
                [
                    -102.76078450778964,
                    23.006782872420278
                ],
                [
                    -103.55900826647355,
                    23.878997905667646
                ],
                [
                    -102.25334226119783,
                    22.118502048282
                ],
                [
                    -116.58054651166421,
                    36.23935459587704
                ],
                [
                    -120.54647074484623,
                    41.57841926173938
                ],
                [
                    -116.95253952317087,
                    36.614804465916166
                ],
                [
                    -114.53458494837756,
                    34.17438031066183
                ],
                [
                    -120.57475621070958,
                    41.30698503623425
                ],
                [
                    -120.1144801209775,
                    39.80612836124875
                ],
                [
                    -120.54904215083381,
                    41.55374342305709
                ],
                [
                    -120.65446979632446,
                    40.54203403708344
                ],
                [
                    -118.99850108645751,
                    38.679778751131366
                ],
                [
                    -102.34456783361883,
                    22.301634083189455
                ],
                [
                    -113.57481590519807,
                    33.439424916184095
                ],
                [
                    -105.26948774936766,
                    25.74803011976915
                ],
                [
                    -103.53050027509198,
                    23.847847368765954
                ],
                [
                    -107.67049413461534,
                    28.673310202536445
                ],
                [
                    -106.58338939659818,
                    27.338351482624837
                ],
                [
                    -113.8307543167126,
                    33.635413021378156
                ],
                [
                    -113.8307543167126,
                    33.635413021378156
                ],
                [
                    -105.71928050227686,
                    26.277230448848947
                ]
            ],
            "timestamps": [
                1671753600,
                1673913600,
                1675296000,
                1681171200,
                1681257600,
                1682208000,
                1683158400,
                1683158400,
                1683504000,
                1684108800,
                1686700800,
                1686873600,
                1687996800,
                1688860800,
                1690243200,
                1690243200,
                1690502400,
                1693785600,
                1693958400,
                1694044800,
                1694217600,
                1695340800,
                1697760000,
                1697846400,
                1698019200,
                1698796800,
                1699488000,
                1701648000,
                1701734400,
                1701820800
            ]
        }
    },
    {
        "data": {
            "id": 4,
            "color": [255, 0, 0, 255],
            "amount": 100,
            "radius": 5000,
            "path": [
                [
                    -121.81160249073287,
                    40.37794892201798
                ],
                [
                    -121.17432237347889,
                    41.813709656269396
                ],
                [
                    -123.7881565598487,
                    39.26394904404092
                ],
                [
                    -122.31559806429756,
                    39.76676880107754
                ],
                [
                    -121.55703329796295,
                    40.76170824799177
                ],
                [
                    -122.53159616725385,
                    39.50483446353164
                ],
                [
                    -123.10416256715384,
                    39.339534479470146
                ],
                [
                    -123.00816341028438,
                    39.350142961635655
                ],
                [
                    -121.32089251477066,
                    41.410815499907756
                ],
                [
                    -122.75616562350206,
                    39.377990227320105
                ],
                [
                    -121.65731813147838,
                    40.565044877407914
                ],
                [
                    -122.01731496973886,
                    40.128487648164736
                ],
                [
                    -123.08016277793647,
                    39.34218660001152
                ],
                [
                    -122.62416678280655,
                    39.392576890297676
                ],
                [
                    -122.60359553490595,
                    39.417523017683
                ],
                [
                    -120.9381815902866,
                    42.46281690818538
                ],
                [
                    -121.23946465849745,
                    41.634645586775335
                ],
                [
                    -123.5961582461098,
                    39.28516600837193
                ],
                [
                    -121.101037302833,
                    42.01515673445022
                ],
                [
                    -123.17616193480593,
                    39.33157811784602
                ],
                [
                    -123.48815919463166,
                    39.297100550808125
                ],
                [
                    -122.86416467498019,
                    39.36605568488391
                ],
                [
                    -121.77045999493167,
                    40.427841176788625
                ],
                [
                    -121.23132187287014,
                    41.657028595462094
                ],
                [
                    -121.49189101294438,
                    40.94077231748583
                ],
                [
                    -122.23331307269515,
                    39.86655331061883
                ],
                [
                    -121.70874625122987,
                    40.5026795589446
                ],
                [
                    -122.05845746554006,
                    40.07859539339409
                ],
                [
                    -121.56517608359027,
                    40.73932523930501
                ],
                [
                    -121.53260494108099,
                    40.82885727405204
                ]
            ],
            "timestamps": [
                1687392000,
                1687478400,
                1687737600,
                1687824000,
                1687910400,
                1688428800,
                1688428800,
                1688860800,
                1689120000,
                1689465600,
                1689465600,
                1689984000,
                1690156800,
                1690761600,
                1691107200,
                1691366400,
                1691539200,
                1691798400,
                1692403200,
                1692489600,
                1692748800,
                1692835200,
                1693267200,
                1693353600,
                1693353600,
                1693699200,
                1693872000,
                1693958400,
                1694995200,
                1695254400
            ]
        }
    },
    {
        "data": {
            "id": 5,
            "color": [255, 0, 0, 255],
            "amount": 100,
            "radius": 5000,
            "path": [
                [
                    -121.84074509192547,
                    37.30297705492794
                ],
                [
                    -121.09932303217485,
                    38.13748771422441
                ],
                [
                    -120.86789649329306,
                    38.882263835288065
                ],
                [
                    -120.96218137950416,
                    38.578836526706574
                ],
                [
                    -121.19789359503191,
                    37.82026825525285
                ],
                [
                    -121.08646600223697,
                    38.178864165394614
                ],
                [
                    -121.72074614583869,
                    37.364956683542474
                ],
                [
                    -121.01789517590163,
                    38.399538571635695
                ],
                [
                    -121.68646073267102,
                    37.38266514886091
                ],
                [
                    -120.24818765028745,
                    41.31407370356564
                ],
                [
                    -121.45503419378936,
                    37.50219728976036
                ],
                [
                    -121.62646125962763,
                    37.41365496316818
                ],
                [
                    -121.00503814596375,
                    38.4409150228059
                ],
                [
                    -121.44646284049745,
                    37.50662440608997
                ],
                [
                    -121.75503155900634,
                    37.34724821822403
                ],
                [
                    -121.93502997813653,
                    37.25427877530224
                ],
                [
                    -121.02218085254759,
                    38.38574642124563
                ],
                [
                    -120.96218137950416,
                    38.578836526706574
                ],
                [
                    -120.74789754720622,
                    39.337882922697865
                ],
                [
                    -120.8636108166471,
                    38.89605598567814
                ],
                [
                    -121.6007471997519,
                    37.426936312157004
                ],
                [
                    -120.84646811006327,
                    38.95122458723841
                ],
                [
                    -120.63475568375291,
                    39.785322344781136
                ],
                [
                    -120.9278959663365,
                    38.68917372982712
                ],
                [
                    -120.56875626340515,
                    40.04632867432971
                ],
                [
                    -120.70075510410068,
                    39.52431601523256
                ],
                [
                    -121.15503682857232,
                    37.95818975915353
                ],
                [
                    -121.25789306807535,
                    37.6271781497919
                ],
                [
                    -121.9178872715527,
                    37.26313300796146
                ],
                [
                    -122.05502892422332,
                    37.19229914668771
                ]
            ],
            "timestamps": [
                1687651200,
                1687651200,
                1687910400,
                1688083200,
                1688169600,
                1688342400,
                1688428800,
                1688947200,
                1688947200,
                1689897600,
                1690156800,
                1690243200,
                1690934400,
                1691193600,
                1692144000,
                1692403200,
                1692748800,
                1692921600,
                1692921600,
                1692921600,
                1693008000,
                1693353600,
                1693440000,
                1693440000,
                1693526400,
                1693526400,
                1693612800,
                1693785600,
                1694131200,
                1694563200
            ]
        }
    },
    {
        "data": {
            "id": 6,
            "color": [255, 0, 0, 255],
            "amount": 100,
            "radius": 5000,
            "path": [
                [
                    -101.61470447585211,
                    21.53912758641103
                ],
                [
                    -101.80108801093618,
                    21.841809695519537
                ],
                [
                    -101.97193958476323,
                    22.11926829553567
                ],
                [
                    -101.93796341951344,
                    23.4007980476297
                ],
                [
                    -101.96417360413473,
                    22.10665654098948
                ],
                [
                    -92.70663932116955,
                    31.973451760622716
                ],
                [
                    -100.1445072681182,
                    28.181115954308904
                ],
                [
                    -100.04257877236911,
                    28.373224191798712
                ],
                [
                    -102.1427911585903,
                    22.3967268955518
                ],
                [
                    -100.12994605443977,
                    28.20855998823602
                ],
                [
                    -74.62176521987709,
                    41.33182256912472
                ],
                [
                    -75.84906490376942,
                    40.83598745554457
                ],
                [
                    -79.34975435047072,
                    38.123867815650655
                ],
                [
                    -83.66648304757956,
                    35.73863520362782
                ],
                [
                    -81.67777258005513,
                    36.534693632578175
                ],
                [
                    -74.08539661739641,
                    41.83467319387697
                ],
                [
                    -74.12771729615132,
                    41.77669613575156
                ],
                [
                    -77.66471402383058,
                    39.74040367659509
                ],
                [
                    -78.73266943625437,
                    38.711264706991145
                ],
                [
                    -77.85009699707221,
                    39.560915070390294
                ],
                [
                    -77.8928776832049,
                    39.51949462280457
                ],
                [
                    -72.74953519235012,
                    43.25891464851455
                ],
                [
                    -85.07924308067525,
                    35.12597389973834
                ],
                [
                    -76.27595175034065,
                    40.66352306821234
                ],
                [
                    -77.49359127929985,
                    39.90608546693799
                ],
                [
                    -82.40380973486565,
                    36.2440691267709
                ],
                [
                    -100.8871291657188,
                    26.781470224026005
                ],
                [
                    -100.75607824261282,
                    27.028466529370046
                ],
                [
                    -94.1268430286071,
                    31.738170504030087
                ],
                [
                    -101.93310968162072,
                    22.056209522804732
                ]
            ],
            "timestamps": [
                1673136000,
                1675900800,
                1680566400,
                1681257600,
                1681344000,
                1683417600,
                1683849600,
                1685664000,
                1687305600,
                1687305600,
                1687910400,
                1688083200,
                1688860800,
                1688860800,
                1689033600,
                1689379200,
                1690588800,
                1691539200,
                1691625600,
                1692057600,
                1692144000,
                1692921600,
                1693094400,
                1694044800,
                1694390400,
                1694995200,
                1696723200,
                1697414400,
                1698969600,
                1700006400
            ]
        }
    }
]